<TEMPLATE ID="swiftunnel3" FORMAT="WRAPPER">


<!-- ******* -->
<ELEMENT ID="CPULPDO" SUB="LINK_VISITED_TEXT_COLOR" TYPE="READONLY" LOAD="THEME::LINK_VISITED_TEXT_COLOR" RAW="1"></ELEMENT>
<ELEMENT ID="CPULPDP" SUB="TABLE_HEADING_FONT_SIZE" TYPE="READONLY" LOAD="THEME::TABLE_HEADING_FONT_SIZE" RAW="1"></ELEMENT>
<ELEMENT ID="CPULPDQ" SUB="DISCLAIMER_FONT_SIZE" TYPE="READONLY" LOAD="THEME::DISCLAIMER_FONT_SIZE" RAW="1"></ELEMENT>
<ELEMENT ID="CPULPDR" SUB="CONTENT_BACKGROUND_COLOR" TYPE="READONLY" LOAD="THEME::CONTENT_BACKGROUND_COLOR" RAW="1"></ELEMENT>
<ELEMENT ID="CPULPDS" SUB="TABLE_LISTING_BACKGROUND_COLOR" TYPE="READONLY" LOAD="THEME::TABLE_LISTING_BACKGROUND_COLOR" RAW="1"></ELEMENT>
<ELEMENT ID="CPULPDT" SUB="CONTENT_TEXT_COLOR" TYPE="READONLY" LOAD="THEME::CONTENT_TEXT_COLOR" RAW="1"></ELEMENT>
<ELEMENT ID="CPULPDU" SUB="TABLE_LISTING_FONT_SIZE" TYPE="READONLY" LOAD="THEME::TABLE_LISTING_FONT_SIZE" RAW="1"></ELEMENT>
<ELEMENT ID="CPULPDV" SUB="TABLE_LISTING_TEXT_COLOR" TYPE="READONLY" LOAD="THEME::TABLE_LISTING_TEXT_COLOR" RAW="1"></ELEMENT>
<ELEMENT ID="CPULPDW" SUB="TABLE_LISTING_FONT_FACE" TYPE="READONLY" LOAD="THEME::TABLE_LISTING_FONT_FACE" RAW="1"></ELEMENT>
<ELEMENT ID="CPULPDX" SUB="CONTENT_FONT_FACE" TYPE="READONLY" LOAD="THEME::CONTENT_FONT_FACE" RAW="1"></ELEMENT>
<ELEMENT ID="CPULPDY" SUB="NAME" TYPE="READONLY" LOAD="THEME::NAME" RAW="1"></ELEMENT>
<ELEMENT ID="CPULPDZ" SUB="DISCLAIMER_FONT_FACE" TYPE="READONLY" LOAD="THEME::DISCLAIMER_FONT_FACE" RAW="1"></ELEMENT>
<ELEMENT ID="CPULPEA" SUB="PRETTY_NAME" TYPE="READONLY" LOAD="THEME::PRETTY_NAME" RAW="1"></ELEMENT>
<ELEMENT ID="CPULPEB" SUB="TABLE_HEADING_BACKGROUND_COLOR" TYPE="READONLY" LOAD="THEME::TABLE_HEADING_BACKGROUND_COLOR" RAW="1"></ELEMENT>
<ELEMENT ID="CPULPEC" SUB="TABLE_LISTING_BACKGROUND_COLOR_ALTERNATE" TYPE="READONLY" LOAD="THEME::TABLE_LISTING_BACKGROUND_COLOR_ALTERNATE" RAW="1"></ELEMENT>
<ELEMENT ID="CPULPED" SUB="LINK_ACTIVE_TEXT_COLOR" TYPE="READONLY" LOAD="THEME::LINK_ACTIVE_TEXT_COLOR" RAW="1"></ELEMENT>
<ELEMENT ID="CPULPEE" SUB="CONTENT_FONT_SIZE" TYPE="READONLY" LOAD="THEME::CONTENT_FONT_SIZE" RAW="1"></ELEMENT>
<ELEMENT ID="CPULPEF" SUB="ALERT_COLOR" TYPE="READONLY" LOAD="THEME::ALERT_COLOR" RAW="1"></ELEMENT>
<ELEMENT ID="CPULPEG" SUB="DISCLAIMER_BACKGROUND_COLOR" TYPE="READONLY" LOAD="THEME::DISCLAIMER_BACKGROUND_COLOR" RAW="1"></ELEMENT>
<ELEMENT ID="CPULPEH" SUB="TABLE_HEADING_FONT_FACE" TYPE="READONLY" LOAD="THEME::TABLE_HEADING_FONT_FACE" RAW="1"></ELEMENT>
<ELEMENT ID="CPULPEI" SUB="TABLE_HEADING_TEXT_COLOR" TYPE="READONLY" LOAD="THEME::TABLE_HEADING_TEXT_COLOR" RAW="1"></ELEMENT>
<ELEMENT ID="CPULPEJ" SUB="DISCLAIMER_TEXT_COLOR" TYPE="READONLY" LOAD="THEME::DISCLAIMER_TEXT_COLOR" RAW="1"></ELEMENT>
<ELEMENT ID="CPULPEK" SUB="LINK_TEXT_COLOR" TYPE="READONLY" LOAD="THEME::LINK_TEXT_COLOR" RAW="1"></ELEMENT>
<ELEMENT ID="CPULPEL" SUB="HOMECATEGORY_URL" TYPE="READONLY" LOAD="URL::HOMECATEGORY_URL" RAW="1"></ELEMENT>
<ELEMENT ID="CPULPEM" SUB="WRAPPER_URL" TYPE="READONLY" LOAD="URL::WRAPPER_URL" RAW="1"></ELEMENT>
<ELEMENT ID="CPULPEN" SUB="CART_URL" TYPE="READONLY" LOAD="URL::CART_URL" RAW="1"></ELEMENT>
<ELEMENT ID="CPULPEO" SUB="SUBSCRIBE_URL" TYPE="READONLY" LOAD="URL::SUBSCRIBE_URL" RAW="1"></ELEMENT>
<ELEMENT ID="CPULPEP" SUB="FEEDBACK_URL" TYPE="READONLY" LOAD="URL::FEEDBACK_URL" RAW="1"></ELEMENT>
<ELEMENT ID="CPULPEQ" SUB="LOGOUT_FUNCTION_URL" TYPE="READONLY" LOAD="URL::LOGOUT_FUNCTION_URL" RAW="1"></ELEMENT>
<ELEMENT ID="CPULPER" SUB="SHIPQUOTE_URL" TYPE="READONLY" LOAD="URL::SHIPQUOTE_URL" RAW="1"></ELEMENT>
<ELEMENT ID="CPULPES" SUB="PRIVACY_URL" TYPE="READONLY" LOAD="URL::PRIVACY_URL" RAW="1"></ELEMENT>
<ELEMENT ID="CPULPET" SUB="SITEBUTTON_URL" TYPE="READONLY" LOAD="URL::SITEBUTTON_URL" RAW="1"></ELEMENT>
<ELEMENT ID="CPULPEU" SUB="HOMEPAGE_URL" TYPE="READONLY" LOAD="URL::HOMEPAGE_URL" RAW="1"></ELEMENT>
<ELEMENT ID="CPULPEV" SUB="COUNTER_URL" TYPE="READONLY" LOAD="URL::COUNTER_URL" RAW="1"></ELEMENT>
<ELEMENT ID="CPULPEW" SUB="RETURNS_URL" TYPE="READONLY" LOAD="URL::RETURNS_URL" RAW="1"></ELEMENT>
<ELEMENT ID="CPULPEX" SUB="PASSWORD_URL" TYPE="READONLY" LOAD="URL::PASSWORD_URL" RAW="1"></ELEMENT>
<ELEMENT ID="CPULPEY" SUB="UPDATE_PAYMENT_URL" TYPE="READONLY" LOAD="URL::UPDATE_PAYMENT_URL" RAW="1"></ELEMENT>
<ELEMENT ID="CPULPEZ" SUB="FORGOT_URL" TYPE="READONLY" LOAD="URL::FORGOT_URL" RAW="1"></ELEMENT>
<ELEMENT ID="CPULPFA" SUB="NAVBUTTON_URL" TYPE="READONLY" LOAD="URL::NAVBUTTON_URL" RAW="1"></ELEMENT>
<ELEMENT ID="CPULPFB" SUB="CONTACT_URL" TYPE="READONLY" LOAD="URL::CONTACT_URL" RAW="1"></ELEMENT>
<ELEMENT ID="CPULPFC" SUB="LOGOUT_URL" TYPE="READONLY" LOAD="URL::LOGOUT_URL" RAW="1"></ELEMENT>
<ELEMENT ID="CPULPFD" SUB="GALLERY_URL" TYPE="READONLY" LOAD="URL::GALLERY_URL" RAW="1"></ELEMENT>
<ELEMENT ID="CPULPFE" SUB="REMOVE_URL" TYPE="READONLY" LOAD="URL::REMOVE_URL" RAW="1"></ELEMENT>
<ELEMENT ID="CPULPFF" SUB="HOME_URL" TYPE="READONLY" LOAD="URL::HOME_URL" RAW="1"></ELEMENT>
<ELEMENT ID="CPULPFG" SUB="ABOUT_ZOOVY_URL" TYPE="READONLY" LOAD="URL::ABOUT_ZOOVY_URL" RAW="1"></ELEMENT>
<ELEMENT ID="CPULPFH" SUB="NEWS_URL" TYPE="READONLY" LOAD="URL::NEWS_URL" RAW="1"></ELEMENT>
<ELEMENT ID="CPULPFI" SUB="SECURE_URL" TYPE="READONLY" LOAD="URL::SECURE_URL" RAW="1"></ELEMENT>
<ELEMENT ID="CPULPFJ" SUB="ABOUT_URL" TYPE="READONLY" LOAD="URL::ABOUT_URL" RAW="1"></ELEMENT>
<ELEMENT ID="CPULPFK" SUB="USERBUTTON_URL" TYPE="READONLY" LOAD="URL::USERBUTTON_URL" RAW="1"></ELEMENT>
<ELEMENT ID="CPULPFL" SUB="CLOSED_URL" TYPE="READONLY" LOAD="URL::CLOSED_URL" RAW="1"></ELEMENT>
<ELEMENT ID="CPULPFM" SUB="FASTORDER_URL" TYPE="READONLY" LOAD="URL::FASTORDER_URL" RAW="1"></ELEMENT>
<ELEMENT ID="CPULPFN" SUB="MAIL_FORM_URL" TYPE="READONLY" LOAD="URL::MAIL_FORM_URL" RAW="1"></ELEMENT>
<ELEMENT ID="CPULPFO" SUB="GRAPHICS_URL" TYPE="READONLY" LOAD="URL::GRAPHICS_URL" RAW="1"></ELEMENT>
<ELEMENT ID="CPULPFP" SUB="IMAGE_URL" TYPE="READONLY" LOAD="URL::IMAGE_URL" RAW="1"></ELEMENT>
<ELEMENT ID="CPULPFQ" SUB="CONTACTUS_URL" TYPE="READONLY" LOAD="URL::CONTACTUS_URL" RAW="1"></ELEMENT>
<ELEMENT ID="CPULPFR" SUB="DYNAMIC_URL" TYPE="READONLY" LOAD="URL::DYNAMIC_URL" RAW="1"></ELEMENT>
<ELEMENT ID="CPULPFS" SUB="NONSECURE_URL" TYPE="READONLY" LOAD="URL::NONSECURE_URL" RAW="1"></ELEMENT>
<ELEMENT ID="CPULPFT" SUB="CONTACT_US_URL" TYPE="READONLY" LOAD="URL::CONTACT_US_URL" RAW="1"></ELEMENT>
<ELEMENT ID="CPULPFU" SUB="SEARCH_URL" TYPE="READONLY" LOAD="URL::SEARCH_URL" RAW="1"></ELEMENT>
<ELEMENT ID="CPULPFV" SUB="ABOUTUS_URL" TYPE="READONLY" LOAD="URL::ABOUTUS_URL" RAW="1"></ELEMENT>
<ELEMENT ID="CPULPFW" SUB="CUSTOMER_MAIN_URL" TYPE="READONLY" LOAD="URL::CUSTOMER_MAIN_URL" RAW="1"></ELEMENT>
<ELEMENT ID="CPULPFX" SUB="MERCHANT_LOGIN_URL" TYPE="READONLY" LOAD="URL::MERCHANT_LOGIN_URL" RAW="1"></ELEMENT>
<ELEMENT ID="CPULPFY" SUB="CATEGORY_URL" TYPE="READONLY" LOAD="URL::CATEGORY_URL" RAW="1"></ELEMENT>
<ELEMENT ID="CPULPFZ" SUB="ADULT_URL" TYPE="READONLY" LOAD="URL::ADULT_URL" RAW="1"></ELEMENT>
<ELEMENT ID="CPULPGA" SUB="CLAIM_URL" TYPE="READONLY" LOAD="URL::CLAIM_URL" RAW="1"></ELEMENT>
<ELEMENT ID="CPULPGB" SUB="CLAIM_MULTI_URL" TYPE="READONLY" LOAD="URL::CLAIM_MULTI_URL" RAW="1"></ELEMENT>
<ELEMENT ID="CPULPGC" SUB="ABOUT_US_URL" TYPE="READONLY" LOAD="URL::ABOUT_US_URL" RAW="1"></ELEMENT>
<ELEMENT ID="CPULPGD" SUB="RESULTS_URL" TYPE="READONLY" LOAD="URL::RESULTS_URL" RAW="1"></ELEMENT>
<ELEMENT ID="CPULPGE" SUB="PRODUCT_URL" TYPE="READONLY" LOAD="URL::PRODUCT_URL" RAW="1"></ELEMENT>
<ELEMENT ID="CPULPGF" SUB="CONTINUE_URL" TYPE="READONLY" LOAD="URL::CONTINUE_URL" RAW="1"></ELEMENT>
<ELEMENT ID="CPULPGG" SUB="REDIR_URL" TYPE="READONLY" LOAD="URL::REDIR_URL" RAW="1"></ELEMENT>
<ELEMENT ID="CPULPGH" SUB="KILL_COOKIES_URL" TYPE="READONLY" LOAD="URL::KILL_COOKIES_URL" RAW="1"></ELEMENT>
<ELEMENT ID="CPULPGI" SUB="LOGIN_URL" TYPE="READONLY" LOAD="URL::LOGIN_URL" RAW="1"></ELEMENT>
<ELEMENT ID="CPULPGJ" SUB="CHECKOUT_URL" TYPE="READONLY" LOAD="URL::CHECKOUT_URL" RAW="1"></ELEMENT>
<ELEMENT ID="CPULPGK" SUB="ORDER_STATUS_URL" TYPE="READONLY" LOAD="URL::ORDER_STATUS_URL" RAW="1"></ELEMENT>
<ELEMENT ID="CPULPGL" SUB="NO_COOKIES_URL" TYPE="READONLY" LOAD="URL::NO_COOKIES_URL" RAW="1"></ELEMENT>
<ELEMENT ID="CPULPGM" SUB="PAYPAL_URL" TYPE="READONLY" LOAD="URL::PAYPAL_URL" RAW="1"></ELEMENT>
<ELEMENT ID="CPULPGN" SUB="CANCEL_ORDER_URL" TYPE="READONLY" LOAD="URL::CANCEL_ORDER_URL" RAW="1"></ELEMENT>
<ELEMENT ID="CPULPGO" SUB="MAIL_CONFIG_URL" TYPE="READONLY" LOAD="URL::MAIL_CONFIG_URL" RAW="1"></ELEMENT>
<ELEMENT ID="CPULPGP" SUB="DISABLED_URL" TYPE="READONLY" LOAD="URL::DISABLED_URL" RAW="1"></ELEMENT>
<ELEMENT ID="CPULPGQ" TYPE="OUTPUT"><HTML><![CDATA[<!DOCTYPE HTML PUBLIC "-//W3C//DTD HTML 4.01 Transitional//EN">
]]></HTML>
</ELEMENT>
<ELEMENT ID="CPULPGR" COLORS="129" TYPE="CONFIG" CATEGORIES="32768" CREATED="20020729" TITLE="Swift Tunnel 3" OCREATED="20020729" PROPERTIES="10" SUBTYPE="C"><CSS><![CDATA[.zbody {  background-color: #000000; }
.zborder {  border: 1px solid #CCCCCC; }
.zbox {  border: 1px solid #99CCFF; }
.zbox_body {  background-color: #003399; color: #FFFFFF; font-family: Arial, Helvetica; font-size: 11pt; }
.zbox_head {  background-color: #99CCFF; color: #003399; font-family: Arial, Helvetica; font-size: 11pt; }
.zcolor {  background-color: #99ccff; color: #003399; }
.zcolor_contrast {  background-color: #99cc8a; color: #7f3399; }
.zcolor_dark {  background-color: #598cbf; color: #000059; }
.zcolor_light {  background-color: #d9ffff; color: #4073d9; }
.zform_button {  background-color: #d9ffff; border: 1px solid #598cbf; color: #598cbf; font-family: Arial, Helvetica; font-size: 8pt; }
.zform_select {  background-color: #FFFFFF; border: 1px solid #598cbf; color: #000000; font-family: Arial, Helvetica; font-size: 8pt; }
.zform_textarea {  background-color: #FFFFFF; border: 1px solid #598cbf; color: #000000; font-family: Arial, Helvetica; font-size: 8pt; }
.zform_textbox {  background-color: #FFFFFF; border: 1px solid #598cbf; color: #000000; font-family: Arial, Helvetica; font-size: 8pt; }
.zhint {  color: #FFFFFF; font-family: Arial, Helvetica; font-size: 8pt; }
.zlink {  color: #99CCFF; }
.zsmall {  color: #FFFFFF; font-family: Arial, Helvetica; font-size: 8pt; }
.ztab0 {  background-color: #a6d9ff; color: #ffffff; font-family: Arial, Helvetica; font-size: 9pt; }
.ztab1 {  background-color: #003399; color: #FFFFFF; font-family: Arial, Helvetica; font-size: 9pt; font-weight: bold; }
.ztabbody {  background-color: #99CCFF; color: #003399; font-family: Arial, Helvetica; font-size: 8pt; }
.ztable_head {  background-color: #99CCFF; color: #003399; font-family: Arial, Helvetica; font-size: 11pt; }
.ztable_row {  color: #FFFFFF; font-family: Arial, Helvetica; font-size: 11pt; }
.ztable_row0 {  background-color: #003399; color: #FFFFFF; font-family: Arial, Helvetica; font-size: 11pt; }
.ztable_row1 {  background-color: #6699CC; color: #FFFFFF; font-family: Arial, Helvetica; font-size: 11pt; }
.ztable_row_small {  color: #FFFFFF; font-family: Arial, Helvetica; font-size: 8pt; }
.ztable_row_title {  color: #FFFFFF; font-family: Arial, Helvetica; font-size: 13pt; font-weight: bold; }
.ztitle {  color: #FFFFFF; font-family: Arial, Helvetica; font-size: 12pt; font-weight: bold; }
.ztitle2 {  color: #FFFFFF; font-family: Arial, Helvetica; font-size: 11pt; font-weight: bold; }
.ztxt {  color: #FFFFFF; font-family: Arial, Helvetica; font-size: 11pt; }
.zwarn {  color: #FFFF00; font-weight: bold; }
]]></CSS>
<THEME><![CDATA[alert_color=FFFF00&content_background_color=000000&content_font_face=Arial%2c+Helvetica&content_font_size=3&content_text_color=FFFFFF&disclaimer_background_color=000000&disclaimer_font_face=Arial%2c+Helvetica&disclaimer_font_size=1&disclaimer_text_color=FFFFFF&link_active_text_color=99CCFF&link_text_color=99CCFF&link_visited_text_color=99CCFF&name=&pretty_name=&table_heading_background_color=99CCFF&table_heading_font_face=Arial%2c+Helvetica&table_heading_font_size=3&table_heading_text_color=003399&table_listing_background_color=003399&table_listing_background_color_alternate=6699CC&table_listing_font_face=Arial%2c+Helvetica&table_listing_font_size=3&table_listing_text_color=FFFFFF]]></THEME>
<SITEBUTTONS><![CDATA[forward=l2_cloudynight|gif|60|20&add_to_cart=l2_cloudynight|gif|83|20&back=l2_cloudynight|gif|63|20&default=l2_cloudynight|gif|78|20&add_to_site=l2_cloudynight|gif|122|32&checkout=l2_cloudynight|gif|68|20&continue_shopping=l2_cloudynight|gif|128|20&update_cart=l2_cloudynight|gif|84|20&cancel=l2_cloudynight|gif|52|20]]></SITEBUTTONS>
</ELEMENT>
<ELEMENT ID="CPULPGS" TYPE="OUTPUT"><HTML><![CDATA[
<html>
<head>
]]></HTML>
</ELEMENT>
<ELEMENT ID="CPULPGT" TYPE="HEAD"></ELEMENT>
<ELEMENT ID="CPULPGU" TYPE="OUTPUT"><HTML><![CDATA[
<style rel="STYLESHEET" type="text/css">
form {display: inline; }
</style>
</head>

<body leftmargin="0" marginheight="0" bottommargin="0" marginwidth="0" rightmargin="0" topmargin="0" bgcolor="#000000" text="#%CONTENT_TEXT_COLOR%" link="#%LINK_TEXT_COLOR%" alink="#%LINK_ACTIVE_TEXT_COLOR%" vlink="#%LINK_VISITED_TEXT_COLOR%">


<table bgcolor="#000000" cellspacing="0" cellpadding="0" border="0" width="100%">
	<tr>
		<td width="49"><a href="%CART_URL%"><img src="%WRAPPER_URL%/cart.jpg" width="49" height="19" alt="" border="0"></a></td>
		<td width="7"><img src="%WRAPPER_URL%/text_break.jpg" width="7" height="19" alt="" border="0"></td>
		<td width="99"><a href="%LOGIN_URL%"><img src="%WRAPPER_URL%/login.jpg" width="99" height="19" alt="" border="0"></a></td>
		<td width="7"><img src="%WRAPPER_URL%/text_break.jpg" width="7" height="19" alt="" border="0"></td>
		<td width="83"><a href="%ABOUT_URL%"><img src="%WRAPPER_URL%/about.jpg" width="83" height="19" alt="" border="0"></a></td>
		<td width="7"><img src="%WRAPPER_URL%/text_break.jpg" width="7" height="19" alt="" border="0"></td>
		<td width="72"><a href="%CONTACT_URL%"><img src="%WRAPPER_URL%/contact.jpg" width="72" height="19" alt="" border="0"></a></td>
		<td width="99%"></td>
		<td nowrap valign="bottom"><form action="%RESULTS_URL%" method="get">
<input type="hidden" name="catalog" value="">
<input type="text" size="12" name="keywords" value="">
<input type="image" border="0" name="NAME" src="%WRAPPER_URL%/submit.jpg">
</form></td>
	</tr>
</table>
<table bgcolor="#000000" cellspacing="0" cellpadding="0" border="0" width="100%">
	<tr>
		<td><img src="%WRAPPER_URL%/middle.jpg" alt="" border="0"></td>
		<td width="99%"></td>
		<td>]]></HTML>
</ELEMENT>
<ELEMENT HEIGHT="68" ID="CPULPGV" WIDTH="200" TYPE="LOGO"></ELEMENT>
<ELEMENT ID="CPULPGW" TYPE="OUTPUT"><HTML><![CDATA[</td>
		<td width="5"><img src="%GRAPHICS_URL%/blank.gif" height="1" width="5"></td>
	</tr>
</table>
<font size="2" face="verdana" color="#F5F9E6">&nbsp;<b>&nbsp;]]></HTML>
</ELEMENT>
<ELEMENT ID="CPULPGX" TYPE="TITLE"></ELEMENT>
<ELEMENT ID="CPULPGY" TYPE="OUTPUT"><HTML><![CDATA[</b></font>
<table bgcolor="#000000" cellspacing="0" cellpadding="9" border="0" width="100%">
	<tr>
		<td width="160"><img src="%GRAPHICS_URL%/blank.gif" height="1" width="160"></td>
		<td width="99%"><img src="%GRAPHICS_URL%/blank.gif" height="5" width="1"></td>
		<td width="1"><img src="%GRAPHICS_URL%/blank.gif" height="1" width="1"></td>
	</tr><tr>
		<td valign="top">]]></HTML>
</ELEMENT>
<ELEMENT ID="CPULPGZ" TYPE="MENU"><HTML><![CDATA[
<!-- CATEGORY -->
<a href="<% load($cat_url);  default("");  print(); %>"><font color="#F5F9E6" face="verdana" size="2"><% load($cat_pretty);  default("");  print(); %></font></a><br>

<!-- /CATEGORY -->

]]></HTML>
</ELEMENT>
<ELEMENT ID="CPULPHA" TYPE="OUTPUT"><HTML><![CDATA[<p>]]></HTML>
</ELEMENT>
<ELEMENT ID="CPULPHB" TYPE="SIDEBAR"></ELEMENT>
<ELEMENT ID="CPULPHC" TYPE="OUTPUT"><HTML><![CDATA[</p></td>
		<td valign="top"><p>]]></HTML>
</ELEMENT>
<ELEMENT ID="CPULPHD" TYPE="BODY"></ELEMENT>
<ELEMENT ID="CPULPHE" TYPE="OUTPUT"><HTML><![CDATA[</p><p>]]></HTML>
</ELEMENT>
<ELEMENT ID="CPULPHF" TYPE="FOOTER"></ELEMENT>
<ELEMENT ID="CPULPHG" TYPE="OUTPUT"><HTML><![CDATA[</p></td>
	</tr>
</table>







</body>
</html>
]]></HTML>
</ELEMENT>

</TEMPLATE>