<TEMPLATE ID="l2_pattern7" FORMAT="WRAPPER">


<!-- ******* -->
<ELEMENT ID="CQLVLCZ" SUB="LINK_TEXT_COLOR" TYPE="READONLY" LOAD="THEME::LINK_TEXT_COLOR" RAW="1"></ELEMENT>
<ELEMENT ID="CQLVLCY" SUB="DISCLAIMER_TEXT_COLOR" TYPE="READONLY" LOAD="THEME::DISCLAIMER_TEXT_COLOR" RAW="1"></ELEMENT>
<ELEMENT ID="CQLVLCX" SUB="TABLE_HEADING_TEXT_COLOR" TYPE="READONLY" LOAD="THEME::TABLE_HEADING_TEXT_COLOR" RAW="1"></ELEMENT>
<ELEMENT ID="CQLVLCW" SUB="TABLE_HEADING_FONT_FACE" TYPE="READONLY" LOAD="THEME::TABLE_HEADING_FONT_FACE" RAW="1"></ELEMENT>
<ELEMENT ID="CQLVLCV" SUB="DISCLAIMER_BACKGROUND_COLOR" TYPE="READONLY" LOAD="THEME::DISCLAIMER_BACKGROUND_COLOR" RAW="1"></ELEMENT>
<ELEMENT ID="CQLVLCU" SUB="ALERT_COLOR" TYPE="READONLY" LOAD="THEME::ALERT_COLOR" RAW="1"></ELEMENT>
<ELEMENT ID="CQLVLCT" SUB="CONTENT_FONT_SIZE" TYPE="READONLY" LOAD="THEME::CONTENT_FONT_SIZE" RAW="1"></ELEMENT>
<ELEMENT ID="CQLVLCS" SUB="LINK_ACTIVE_TEXT_COLOR" TYPE="READONLY" LOAD="THEME::LINK_ACTIVE_TEXT_COLOR" RAW="1"></ELEMENT>
<ELEMENT ID="CQLVLCR" SUB="TABLE_LISTING_BACKGROUND_COLOR_ALTERNATE" TYPE="READONLY" LOAD="THEME::TABLE_LISTING_BACKGROUND_COLOR_ALTERNATE" RAW="1"></ELEMENT>
<ELEMENT ID="CQLVLCQ" SUB="TABLE_HEADING_BACKGROUND_COLOR" TYPE="READONLY" LOAD="THEME::TABLE_HEADING_BACKGROUND_COLOR" RAW="1"></ELEMENT>
<ELEMENT ID="CQLVLCP" SUB="PRETTY_NAME" TYPE="READONLY" LOAD="THEME::PRETTY_NAME" RAW="1"></ELEMENT>
<ELEMENT ID="CQLVLCO" SUB="DISCLAIMER_FONT_FACE" TYPE="READONLY" LOAD="THEME::DISCLAIMER_FONT_FACE" RAW="1"></ELEMENT>
<ELEMENT ID="CQLVLCN" SUB="NAME" TYPE="READONLY" LOAD="THEME::NAME" RAW="1"></ELEMENT>
<ELEMENT ID="CQLVLCM" SUB="CONTENT_FONT_FACE" TYPE="READONLY" LOAD="THEME::CONTENT_FONT_FACE" RAW="1"></ELEMENT>
<ELEMENT ID="CQLVLCL" SUB="TABLE_LISTING_FONT_FACE" TYPE="READONLY" LOAD="THEME::TABLE_LISTING_FONT_FACE" RAW="1"></ELEMENT>
<ELEMENT ID="CQLVLCK" SUB="TABLE_LISTING_TEXT_COLOR" TYPE="READONLY" LOAD="THEME::TABLE_LISTING_TEXT_COLOR" RAW="1"></ELEMENT>
<ELEMENT ID="CQLVLCJ" SUB="TABLE_LISTING_FONT_SIZE" TYPE="READONLY" LOAD="THEME::TABLE_LISTING_FONT_SIZE" RAW="1"></ELEMENT>
<ELEMENT ID="CQLVLCI" SUB="CONTENT_TEXT_COLOR" TYPE="READONLY" LOAD="THEME::CONTENT_TEXT_COLOR" RAW="1"></ELEMENT>
<ELEMENT ID="CQLVLCH" SUB="TABLE_LISTING_BACKGROUND_COLOR" TYPE="READONLY" LOAD="THEME::TABLE_LISTING_BACKGROUND_COLOR" RAW="1"></ELEMENT>
<ELEMENT ID="CQLVLCG" SUB="CONTENT_BACKGROUND_COLOR" TYPE="READONLY" LOAD="THEME::CONTENT_BACKGROUND_COLOR" RAW="1"></ELEMENT>
<ELEMENT ID="CQLVLCF" SUB="DISCLAIMER_FONT_SIZE" TYPE="READONLY" LOAD="THEME::DISCLAIMER_FONT_SIZE" RAW="1"></ELEMENT>
<ELEMENT ID="CQLVLCE" SUB="TABLE_HEADING_FONT_SIZE" TYPE="READONLY" LOAD="THEME::TABLE_HEADING_FONT_SIZE" RAW="1"></ELEMENT>
<ELEMENT ID="CQLVLCD" SUB="LINK_VISITED_TEXT_COLOR" TYPE="READONLY" LOAD="THEME::LINK_VISITED_TEXT_COLOR" RAW="1"></ELEMENT>
<ELEMENT ID="CQQZLEI" SUB="HOMECATEGORY_URL" TYPE="READONLY" LOAD="URL::HOMECATEGORY_URL" RAW="1"></ELEMENT>
<ELEMENT ID="CQQZLEJ" SUB="WRAPPER_URL" TYPE="READONLY" LOAD="URL::WRAPPER_URL" RAW="1"></ELEMENT>
<ELEMENT ID="CQQZLEK" SUB="CART_URL" TYPE="READONLY" LOAD="URL::CART_URL" RAW="1"></ELEMENT>
<ELEMENT ID="CQQZLEL" SUB="SUBSCRIBE_URL" TYPE="READONLY" LOAD="URL::SUBSCRIBE_URL" RAW="1"></ELEMENT>
<ELEMENT ID="CQQZLEM" SUB="FEEDBACK_URL" TYPE="READONLY" LOAD="URL::FEEDBACK_URL" RAW="1"></ELEMENT>
<ELEMENT ID="CQQZLEN" SUB="LOGOUT_FUNCTION_URL" TYPE="READONLY" LOAD="URL::LOGOUT_FUNCTION_URL" RAW="1"></ELEMENT>
<ELEMENT ID="CQQZLEO" SUB="SHIPQUOTE_URL" TYPE="READONLY" LOAD="URL::SHIPQUOTE_URL" RAW="1"></ELEMENT>
<ELEMENT ID="CQQZLEP" SUB="PRIVACY_URL" TYPE="READONLY" LOAD="URL::PRIVACY_URL" RAW="1"></ELEMENT>
<ELEMENT ID="CQQZLEQ" SUB="SITEBUTTON_URL" TYPE="READONLY" LOAD="URL::SITEBUTTON_URL" RAW="1"></ELEMENT>
<ELEMENT ID="CQQZLER" SUB="HOMEPAGE_URL" TYPE="READONLY" LOAD="URL::HOMEPAGE_URL" RAW="1"></ELEMENT>
<ELEMENT ID="CQQZLES" SUB="COUNTER_URL" TYPE="READONLY" LOAD="URL::COUNTER_URL" RAW="1"></ELEMENT>
<ELEMENT ID="CQQZLET" SUB="RETURNS_URL" TYPE="READONLY" LOAD="URL::RETURNS_URL" RAW="1"></ELEMENT>
<ELEMENT ID="CQQZLEU" SUB="PASSWORD_URL" TYPE="READONLY" LOAD="URL::PASSWORD_URL" RAW="1"></ELEMENT>
<ELEMENT ID="CQQZLEV" SUB="UPDATE_PAYMENT_URL" TYPE="READONLY" LOAD="URL::UPDATE_PAYMENT_URL" RAW="1"></ELEMENT>
<ELEMENT ID="CQQZLEW" SUB="FORGOT_URL" TYPE="READONLY" LOAD="URL::FORGOT_URL" RAW="1"></ELEMENT>
<ELEMENT ID="CQQZLEX" SUB="NAVBUTTON_URL" TYPE="READONLY" LOAD="URL::NAVBUTTON_URL" RAW="1"></ELEMENT>
<ELEMENT ID="CQQZLEY" SUB="CONTACT_URL" TYPE="READONLY" LOAD="URL::CONTACT_URL" RAW="1"></ELEMENT>
<ELEMENT ID="CQQZLEZ" SUB="LOGOUT_URL" TYPE="READONLY" LOAD="URL::LOGOUT_URL" RAW="1"></ELEMENT>
<ELEMENT ID="CQQZLFA" SUB="GALLERY_URL" TYPE="READONLY" LOAD="URL::GALLERY_URL" RAW="1"></ELEMENT>
<ELEMENT ID="CQQZLFB" SUB="REMOVE_URL" TYPE="READONLY" LOAD="URL::REMOVE_URL" RAW="1"></ELEMENT>
<ELEMENT ID="CQQZLFC" SUB="HOME_URL" TYPE="READONLY" LOAD="URL::HOME_URL" RAW="1"></ELEMENT>
<ELEMENT ID="CQQZLFD" SUB="ABOUT_ZOOVY_URL" TYPE="READONLY" LOAD="URL::ABOUT_ZOOVY_URL" RAW="1"></ELEMENT>
<ELEMENT ID="CQQZLFE" SUB="NEWS_URL" TYPE="READONLY" LOAD="URL::NEWS_URL" RAW="1"></ELEMENT>
<ELEMENT ID="CQQZLFF" SUB="SECURE_URL" TYPE="READONLY" LOAD="URL::SECURE_URL" RAW="1"></ELEMENT>
<ELEMENT ID="CQQZLFG" SUB="ABOUT_URL" TYPE="READONLY" LOAD="URL::ABOUT_URL" RAW="1"></ELEMENT>
<ELEMENT ID="CQQZLFH" SUB="USERBUTTON_URL" TYPE="READONLY" LOAD="URL::USERBUTTON_URL" RAW="1"></ELEMENT>
<ELEMENT ID="CQQZLFI" SUB="CLOSED_URL" TYPE="READONLY" LOAD="URL::CLOSED_URL" RAW="1"></ELEMENT>
<ELEMENT ID="CQQZLFJ" SUB="FASTORDER_URL" TYPE="READONLY" LOAD="URL::FASTORDER_URL" RAW="1"></ELEMENT>
<ELEMENT ID="CQQZLFK" SUB="MAIL_FORM_URL" TYPE="READONLY" LOAD="URL::MAIL_FORM_URL" RAW="1"></ELEMENT>
<ELEMENT ID="CQQZLFL" SUB="GRAPHICS_URL" TYPE="READONLY" LOAD="URL::GRAPHICS_URL" RAW="1"></ELEMENT>
<ELEMENT ID="CQQZLFM" SUB="IMAGE_URL" TYPE="READONLY" LOAD="URL::IMAGE_URL" RAW="1"></ELEMENT>
<ELEMENT ID="CQQZLFN" SUB="CONTACTUS_URL" TYPE="READONLY" LOAD="URL::CONTACTUS_URL" RAW="1"></ELEMENT>
<ELEMENT ID="CQQZLFO" SUB="DYNAMIC_URL" TYPE="READONLY" LOAD="URL::DYNAMIC_URL" RAW="1"></ELEMENT>
<ELEMENT ID="CQQZLFP" SUB="NONSECURE_URL" TYPE="READONLY" LOAD="URL::NONSECURE_URL" RAW="1"></ELEMENT>
<ELEMENT ID="CQQZLFQ" SUB="CONTACT_US_URL" TYPE="READONLY" LOAD="URL::CONTACT_US_URL" RAW="1"></ELEMENT>
<ELEMENT ID="CQQZLFR" SUB="SEARCH_URL" TYPE="READONLY" LOAD="URL::SEARCH_URL" RAW="1"></ELEMENT>
<ELEMENT ID="CQQZLFS" SUB="ABOUTUS_URL" TYPE="READONLY" LOAD="URL::ABOUTUS_URL" RAW="1"></ELEMENT>
<ELEMENT ID="CQQZLFT" SUB="CUSTOMER_MAIN_URL" TYPE="READONLY" LOAD="URL::CUSTOMER_MAIN_URL" RAW="1"></ELEMENT>
<ELEMENT ID="CQQZLFU" SUB="MERCHANT_LOGIN_URL" TYPE="READONLY" LOAD="URL::MERCHANT_LOGIN_URL" RAW="1"></ELEMENT>
<ELEMENT ID="CQQZLFV" SUB="CATEGORY_URL" TYPE="READONLY" LOAD="URL::CATEGORY_URL" RAW="1"></ELEMENT>
<ELEMENT ID="CQQZLFW" SUB="ADULT_URL" TYPE="READONLY" LOAD="URL::ADULT_URL" RAW="1"></ELEMENT>
<ELEMENT ID="CQQZLFX" SUB="CLAIM_URL" TYPE="READONLY" LOAD="URL::CLAIM_URL" RAW="1"></ELEMENT>
<ELEMENT ID="CQQZLFY" SUB="CLAIM_MULTI_URL" TYPE="READONLY" LOAD="URL::CLAIM_MULTI_URL" RAW="1"></ELEMENT>
<ELEMENT ID="CQQZLFZ" SUB="ABOUT_US_URL" TYPE="READONLY" LOAD="URL::ABOUT_US_URL" RAW="1"></ELEMENT>
<ELEMENT ID="CQQZLGA" SUB="RESULTS_URL" TYPE="READONLY" LOAD="URL::RESULTS_URL" RAW="1"></ELEMENT>
<ELEMENT ID="CQQZLGB" SUB="PRODUCT_URL" TYPE="READONLY" LOAD="URL::PRODUCT_URL" RAW="1"></ELEMENT>
<ELEMENT ID="CQQZLGC" SUB="CONTINUE_URL" TYPE="READONLY" LOAD="URL::CONTINUE_URL" RAW="1"></ELEMENT>
<ELEMENT ID="CQQZLGD" SUB="REDIR_URL" TYPE="READONLY" LOAD="URL::REDIR_URL" RAW="1"></ELEMENT>
<ELEMENT ID="CQQZLGE" SUB="KILL_COOKIES_URL" TYPE="READONLY" LOAD="URL::KILL_COOKIES_URL" RAW="1"></ELEMENT>
<ELEMENT ID="CQQZLGF" SUB="LOGIN_URL" TYPE="READONLY" LOAD="URL::LOGIN_URL" RAW="1"></ELEMENT>
<ELEMENT ID="CQQZLGG" SUB="CHECKOUT_URL" TYPE="READONLY" LOAD="URL::CHECKOUT_URL" RAW="1"></ELEMENT>
<ELEMENT ID="CQQZLGH" SUB="ORDER_STATUS_URL" TYPE="READONLY" LOAD="URL::ORDER_STATUS_URL" RAW="1"></ELEMENT>
<ELEMENT ID="CQQZLGI" SUB="NO_COOKIES_URL" TYPE="READONLY" LOAD="URL::NO_COOKIES_URL" RAW="1"></ELEMENT>
<ELEMENT ID="CQQZLGJ" SUB="PAYPAL_URL" TYPE="READONLY" LOAD="URL::PAYPAL_URL" RAW="1"></ELEMENT>
<ELEMENT ID="CQQZLGK" SUB="CANCEL_ORDER_URL" TYPE="READONLY" LOAD="URL::CANCEL_ORDER_URL" RAW="1"></ELEMENT>
<ELEMENT ID="CQQZLGL" SUB="WISHLIST_URL" TYPE="READONLY" LOAD="URL::WISHLIST_URL" RAW="1"></ELEMENT>
<ELEMENT ID="CQQZLGM" SUB="MAIL_CONFIG_URL" TYPE="READONLY" LOAD="URL::MAIL_CONFIG_URL" RAW="1"></ELEMENT>
<ELEMENT ID="CQQZLGN" SUB="DISABLED_URL" TYPE="READONLY" LOAD="URL::DISABLED_URL" RAW="1"></ELEMENT>
<ELEMENT ID="CQQZLGO" COLORS="34" TYPE="CONFIG" CATEGORIES="16384" CREATED="20020328" TITLE="Raging Bull" PROPERTIES="2" OCREATED="20020328" SUBTYPE="C"><CSS><![CDATA[.zbody {  background-color: #DF0000; }
.zborder {  border: 1px solid #CCCCCC; }
.zbox {  border: 1px solid #000000; }
.zbox_body {  background-color: #FFFFFF; color: #000000; font-family: Arial, Helvetica; font-size: 11pt; }
.zbox_head {  background-color: #000000; color: #FFFFFF; font-family: Arial, Helvetica; font-size: 11pt; }
.zcolor {  background-color: #000000; color: #ffffff; }
.zcolor_contrast {  background-color: #757575; color: #101010; }
.zcolor_dark {  background-color: #000000; color: #bfbfbf; }
.zcolor_light {  background-color: #404040; color: #ffffff; }
.zform_button {  background-color: #404040; border: 1px solid #000000; color: #000000; font-family: Arial, Helvetica; font-size: 8pt; }
.zform_select {  background-color: #FFFFFF; border: 1px solid #000000; color: #000000; font-family: Arial, Helvetica; font-size: 8pt; }
.zform_textarea {  background-color: #FFFFFF; border: 1px solid #000000; color: #000000; font-family: Arial, Helvetica; font-size: 8pt; }
.zform_textbox {  background-color: #FFFFFF; border: 1px solid #000000; color: #000000; font-family: Arial, Helvetica; font-size: 8pt; }
.zhint {  color: #FFFFFF; font-family: Arial, Helvetica; font-size: 8pt; }
.zlink {  color: #FFFFFF; }
.zsmall {  color: #FFFFFF; font-family: Arial, Helvetica; font-size: 8pt; }
.ztab0 {  background-color: #d9d9d9; color: #404040; font-family: Arial, Helvetica; font-size: 9pt; }
.ztab1 {  background-color: #FFFFFF; color: #000000; font-family: Arial, Helvetica; font-size: 9pt; font-weight: bold; }
.ztabbody {  background-color: #000000; color: #FFFFFF; font-family: Arial, Helvetica; font-size: 8pt; }
.ztable_head {  background-color: #000000; color: #FFFFFF; font-family: Arial, Helvetica; font-size: 11pt; }
.ztable_row {  color: #000000; font-family: Arial, Helvetica; font-size: 11pt; }
.ztable_row0 {  background-color: #FFFFFF; color: #000000; font-family: Arial, Helvetica; font-size: 11pt; }
.ztable_row1 {  background-color: #999999; color: #000000; font-family: Arial, Helvetica; font-size: 11pt; }
.ztable_row_small {  color: #000000; font-family: Arial, Helvetica; font-size: 8pt; }
.ztable_row_title {  color: #000000; font-family: Arial, Helvetica; font-size: 13pt; font-weight: bold; }
.ztitle {  color: #FFFFFF; font-family: Arial, Helvetica; font-size: 12pt; font-weight: bold; }
.ztitle2 {  color: #FFFFFF; font-family: Arial, Helvetica; font-size: 11pt; font-weight: bold; }
.ztxt {  color: #FFFFFF; font-family: Arial, Helvetica; font-size: 11pt; }
.zwarn {  color: #FFFFFF; font-weight: bold; }
]]></CSS>
<THEME><![CDATA[alert_color=FFFFFF&content_background_color=DF0000&content_font_face=Arial%2c+Helvetica&content_font_size=3&content_text_color=FFFFFF&disclaimer_background_color=DF0000&disclaimer_font_face=Arial%2c+Helvetica&disclaimer_font_size=1&disclaimer_text_color=FFFFFF&link_active_text_color=FFFFFF&link_text_color=FFFFFF&link_visited_text_color=FFFFFF&name=&pretty_name=&table_heading_background_color=000000&table_heading_font_face=Arial%2c+Helvetica&table_heading_font_size=3&table_heading_text_color=FFFFFF&table_listing_background_color=FFFFFF&table_listing_background_color_alternate=999999&table_listing_font_face=Arial%2c+Helvetica&table_listing_font_size=3&table_listing_text_color=000000]]></THEME>
<SITEBUTTONS><![CDATA[forward=l2_pattern7|gif|76|28&add_to_cart=l2_pattern7|gif|108|28&back=l2_pattern7|gif|80|28&default=l2_pattern7|gif|100|28&add_to_site=l2_pattern7|gif|122|32&checkout=l2_pattern7|gif|84|28&continue_shopping=l2_pattern7|gif|164|28&update_cart=l2_pattern7|gif|108|28&cancel=l2_pattern7|gif|64|28]]></SITEBUTTONS>
</ELEMENT>
<ELEMENT ID="CQQZLGP" TYPE="OUTPUT"><HTML><![CDATA[<!DOCTYPE HTML PUBLIC "-//W3C//DTD HTML 4.0 Transitional//EN">
<html>
<head>
]]></HTML>
</ELEMENT>
<ELEMENT ID="CQQZLGQ" TYPE="HEAD"></ELEMENT>
<ELEMENT ID="CQQZLGR" TYPE="OUTPUT"><HTML><![CDATA[
<map name="right">
	<area href="%CART_URL%" shape="rect" coords="15,46 107,80" alt="Shopping Cart">
	<area href="%SEARCH_URL%" shape="rect" coords="109,47 200,79" alt="Search">
	<area href="%ABOUT_URL%" shape="rect" coords="202,48 294,79" alt="About Us">
	<area href="%CONTACT_URL%" shape="rect" coords="297,48 385,78" alt="Contact Us">
</map>
<script language="JavaScript">
<!--
initialized = 0;
]]></HTML>
</ELEMENT>
<ELEMENT ID="CQQZLGS" WIDTH="130" TYPE="MENU" BUTTONTYPE="l2_pattern7_on"><HTML><![CDATA[
<!-- CATEGORY -->
rollover_<% load($cat_num);  default("");  print(); %>_on = new Image;<% load("
");  default("");  print(); %>rollover_<% load($cat_num);  default("");  print(); %>_on.src = "<% load($button_imgsrc);  default("");  print(); %>";<% load("
");  default("");  print(); %>

<!-- /CATEGORY -->

]]></HTML>
</ELEMENT>
<ELEMENT ID="CQQZLGT" WIDTH="130" TYPE="MENU" BUTTONTYPE="l2_pattern7_off"><HTML><![CDATA[
<!-- CATEGORY -->
rollover_<% load($cat_num);  default("");  print(); %>_off = new Image;<% load("
");  default("");  print(); %>rollover_<% load($cat_num);  default("");  print(); %>_off.src = "<% load($button_imgsrc);  default("");  print(); %>";<% load("
");  default("");  print(); %>

<!-- /CATEGORY -->

]]></HTML>
</ELEMENT>
<ELEMENT ID="CQQZLGU" TYPE="OUTPUT"><HTML><![CDATA[initialized = 1;
function on(imageNumber) {
if (!initialized || !document.images) return;
document.images[eval("\"roll_"+imageNumber+"\"")].src = eval("rollover_"+imageNumber+"_on.src");
}
function off(imageNumber) {
if (!initialized || !document.images) return;
document.images[eval("\"roll_"+imageNumber+"\"")].src = eval("rollover_"+imageNumber+"_off.src");
}
// -->
</script>
</head> 
<body background="%WRAPPER_URL%/background.gif" text="#%CONTENT_TEXT_COLOR%" link="#%LINK_TEXT_COLOR%" alink="#%LINK_ACTIVE_TEXT_COLOR%" vlink="#%LINK_VISITED_TEXT_COLOR%" marginheight="0" marginwidth="0" topmargin="0" leftmargin="0">
<table width="100%" height="100" border="0" cellpadding="0" cellspacing="0">
	<tr>
		<td background="%WRAPPER_URL%/topbar_background.gif" border="0" cellpadding="0" cellspacing="0" width="100%" align="left">
			<table background="%WRAPPER_URL%/topbar_background.gif" width="100%" height="100" border="0" cellpadding="0" cellspacing="0">
				<tr>
					<td align="left" valign="top" width="33" background=""><img src="%WRAPPER_URL%/leftmap.gif" width="33"  height="100" border="0"></td>
					<td align="left" valign="middle" width="100%">
						<table background="" border="0" cellpadding="0" cellspacing="0">
							<tr>
								<td background="%WRAPPER_URL%/logo_background.gif" width="1" height="1" align="left" valign="top"><a href="%HOME_URL%">]]></HTML>
</ELEMENT>
<ELEMENT HEIGHT="80" ID="CQQZLGV" WIDTH="160" TYPE="LOGO"></ELEMENT>
<ELEMENT ID="CQQZLGW" TYPE="OUTPUT"><HTML><![CDATA[</a></td>
							</tr>
						</table>
					</td>
					<td align="right" valign="bottom" width="400" background=""><img src="%WRAPPER_URL%/rightmap.gif" width="400"  height="100" usemap="#right" border="0"></td>
				</tr>
			</table>
		</td>
	</tr>
</table>
<table border="0" cellpadding="0" cellspacing="0" width="100%">
	<tr>
		<td align="left" valign="top">
			<table border="0" cellpadding="0" cellspacing="0">
				<tr>
					<td valign="top" align="center" height="40"><img src="%WRAPPER_URL%/topmap.gif" width="145" height="40" border="0"></td>
				</tr>
				<tr>
					<td valign="top" align="center" background="%WRAPPER_URL%/sidebar_background.gif"><img src="%GRAPHICS_URL%/blank.gif" width="145" height="1"><br>
						<table border="0" cellpadding="" cellspacing="0">
							<tr>
								<td align="center">]]></HTML>
</ELEMENT>
<ELEMENT ID="CQQZLGX" WIDTH="130" TYPE="MENU" BUTTONTYPE="l2_pattern7_off"><HTML><![CDATA[
<!-- CATEGORY -->
<a href="<% load($cat_url);  default("");  print(); %>" OnMouseOver="on(<% load($cat_num);  default("");  print(); %>)" OnMouseOut="off(<% load($cat_num);  default("");  print(); %>)"><img src="<% load($button_imgsrc);  default("");  print(); %>" width="<% load($button_width);  default("");  print(); %>" height="<% load($button_height);  default("");  print(); %>" border="0" name="roll_<% load($cat_num);  default("");  print(); %>"></a><br>

<!-- /CATEGORY -->

]]></HTML>
</ELEMENT>
<ELEMENT ID="CQQZLGY" TYPE="OUTPUT"><HTML><![CDATA[</td>
							</tr>
						</table>
					</td>
				</tr>
				<tr>
					<td valign="top" align="center" height="41"><img src="%WRAPPER_URL%/bottommap.gif" width="145" height="41" border="0"></td>
				</tr>
				<tr>
					<td valign="top" align="center" background="">]]></HTML>
</ELEMENT>
<ELEMENT ID="CQQZLGZ" TYPE="SIDEBAR"></ELEMENT>
<ELEMENT ID="CQQZLHA" TYPE="OUTPUT"><HTML><![CDATA[</td>
				</tr>
			</table>
		</td>
		<td align="left" valign="top" width="100%">
			<table background="%WRAPPER_URL%/title_background.gif" border="0" cellpadding="0" cellspacing="0" width="100%">
				<tr>
					<td valign="top" align="left"><img src="%WRAPPER_URL%/corner.gif"  width="50" height="38"></td>
					<td width="100%" align="left" valign="bottom">
						<table cellpadding="5">
							<tr>
								 <td background=""><font color="#ffffff" face="Arial, Helvetica"  size="4">]]></HTML>
</ELEMENT>
<ELEMENT ID="CQQZLHB" TYPE="TITLE"></ELEMENT>
<ELEMENT ID="CQQZLHC" TYPE="OUTPUT"><HTML><![CDATA[</font></td>
							</tr>
						</table>
					</td>
				</tr>
			</table>
			<table border="0" cellpadding="10" cellspacing="0" width="100%">
				<tr>
					<td width="100%" align="left" valign="top">
]]></HTML>
</ELEMENT>
<ELEMENT ID="CQQZLHD" TYPE="BODY"></ELEMENT>
<ELEMENT ID="CQQZLHE" TYPE="OUTPUT"><HTML><![CDATA[
<br>
<br>
]]></HTML>
</ELEMENT>
<ELEMENT ID="CQQZLHF" TYPE="FOOTER" TRANSPARENT="TRUE"></ELEMENT>
<ELEMENT ID="CQQZLHG" TYPE="OUTPUT"><HTML><![CDATA[
					</td>
				</tr>
			</table>
		</td>
	</tr>
</table>

</body>
</html>
]]></HTML>
</ELEMENT>

</TEMPLATE>